MANIFEST.in
README.rst
setup.py
docs/HISTORY.txt
src/mobi/__init__.py
src/mobi.interfaces.egg-info/PKG-INFO
src/mobi.interfaces.egg-info/SOURCES.txt
src/mobi.interfaces.egg-info/dependency_links.txt
src/mobi.interfaces.egg-info/namespace_packages.txt
src/mobi.interfaces.egg-info/requires.txt
src/mobi.interfaces.egg-info/top_level.txt
src/mobi/interfaces/__init__.py
src/mobi/interfaces/configure.zcml
src/mobi/interfaces/devices.py
src/mobi/interfaces/rendering.py
src/mobi/interfaces/schema.py