Metadata-Version: 1.0
Name: mobi.interfaces
Version: 1.0
Summary: Mobile libs interfaces package
Home-page: http://infrae.com/
Author: Antonin Amand at Infrae
Author-email: info@infrae.com
License: BSD
Platform: UNKNOWN
